{
    "1": {
        "m_file": "partyloop1",
        "m_title": "Party On",
        "m_artist": "Bin Party"
    },
    "2": {
        "m_file": "partyloop2",
        "m_title": "Party Now",
        "m_artist": "Bin Party"
    },
    "3": {
        "m_file": "partyloop3",
        "m_title": "Party Slow",
        "m_artist": "Bin Party"
    },
    "4": {
        "m_file": "partyloop4",
        "m_title": "Funk Party",
        "m_artist": "Bin Party"
    },
    "5": {
        "m_file": "Enemy",
        "m_title": "Enemy",
        "m_artist": "Dan Morrissey"
    },
    "6": {
        "m_file": "AlteredStates",
        "m_title": "Altered States",
        "m_artist": "James Treweek"
    },
    "7": {
        "m_file": "DivaFever",
        "m_title": "Diva Fever",
        "m_artist": "Redfor-Courtie"
    },
    "8": {
        "m_file": "Scratch",
        "m_title": "Scratch",
        "m_artist": "Tim Butler"
    },
    "9": {
        "m_file": "prodigious",
        "m_title": "Prodigious Party",
        "m_artist": "Prodigious"
    },
    "10": {
        "m_file": "ubisoft/Mus_01_Sane_Cusurgale",
        "m_title": "",
        "m_artist": "Bin Party"
    },
    "11": {
        "m_file": "ubisoft/Mus_05_Costel_Solo",
        "m_title": "",
        "m_artist": "Bin Party"
    },
    "12": {
        "m_file": "ubisoft/Mus_07_Ruseasca_Cu_Gigel",
        "m_title": "",
        "m_artist": "Bin Party"
    },
    "13": {
        "m_file": "ubisoft/Mus_14_Florine",
        "m_title": "",
        "m_artist": "Bin Party"
    },
    "14": {
        "m_file": "ubisoft/Mus_Jingle_Score_A",
        "m_title": "",
        "m_artist": "Bin Party"
    },
    "15": {
        "m_file": "ubisoft/Mus_Jingle_Score_B",
        "m_title": "",
        "m_artist": "Bin Party"
    },
    "16": {
        "m_file": "ubisoft/Mus_Jingle_Score_C",
        "m_title": "",
        "m_artist": "Bin Party"
    },
    "17": {
        "m_file": "ubisoft/Mus_Jingle_Score_S",
        "m_title": "",
        "m_artist": "Bin Party"
    },
    "18": {
        "m_file": "alvin2/bringiton",
        "m_title": "",
        "m_artist": "Bin Party"
    },
    "19": {
        "m_file": "alvin2/Inthefamily",
        "m_title": "",
        "m_artist": "Bin Party"
    },
    "20": {
        "m_file": "alvin2/itsok",
        "m_title": "",
        "m_artist": "Bin Party"
    },
    "21": {
        "m_file": "christmas/Glam_Tidings",
        "m_title": "",
        "m_artist": "Bin Party"
    },
    "22": {
        "m_file": "christmas/Jingle_Bell_Jump",
        "m_title": "",
        "m_artist": "Bin Party"
    },
    "23": {
        "m_file": "christmas/Rock_The_Halls",
        "m_title": "",
        "m_artist": "Bin Party"
    },
    "24": {
        "m_file": "christmas/Happy_Christmas",
        "m_title": "",
        "m_artist": "Bin Party"
    },
    "25": {
        "m_file": "beachParty/steel_drums",
        "m_title": "Steel Drums",
        "m_artist": "Bin Party"
    },
    "26": {
        "m_file": "beachParty/surfing_dude",
        "m_title": "Surfing Dude",
        "m_artist": "Bin Party"
    },
    "27": {
        "m_file": "beachParty/hawaii3",
        "m_title": "Hawaai 3",
        "m_artist": "Bin Party"
    },
    "28": {
        "m_file": "beachParty/hawaii2",
        "m_title": "Hawaai 2",
        "m_artist": "Bin Party"
    },
    "29": {
        "m_file": "smb/drum_and_bossa_56k",
        "m_title": "smb",
        "m_artist": "Bin Party"
    },
    "30": {
        "m_file": "clubfling/Get_Up_and_Dance",
        "m_title": "Club Fling Music",
        "m_artist": "Bin Party"
    },
    "31": {
        "m_file": "clubfling/Music_Club",
        "m_title": "Club Fling Music",
        "m_artist": "Bin Party"
    },
    "32": {
        "m_file": "clubfling/Super_Fly",
        "m_title": "Club Fling Music",
        "m_artist": "Bin Party"
    },
    "33": {
        "m_file": "flemManor/firePlace",
        "m_title": "Flem Manor Fireplace",
        "m_artist": "Bin Party"
    },
    "34": {
        "m_file": "mulchIsland/jungle",
        "m_title": "Mulch Island Jungle",
        "m_artist": "Bin Party"
    },
    "35": {
        "m_file": "mulchIsland/BeachAndWaves",
        "m_title": "Mulch Island Beach",
        "m_artist": "Bin Party"
    },
    "36": {
        "m_file": "ufo/UFO1",
        "m_title": "UFO Party",
        "m_artist": "Bin Party"
    },
    "37": {
        "m_file": "ufo/UFO2",
        "m_title": "UFO Party",
        "m_artist": "Bin Party"
    },
    "38": {
        "m_file": "halloween/nightmare",
        "m_title": "Halloween Party",
        "m_artist": "Bin Party"
    },
    "39": {
        "m_file": "halloween/spooky_western",
        "m_title": "Halloween Party",
        "m_artist": "Bin Party"
    },
    "40": {
        "m_file": "halloween/spooky_western",
        "m_title": "Halloween Party",
        "m_artist": "Bin Party"
    },
    "41": {
        "m_file": "rabbidsParty/rabbidsPartyTheme",
        "m_title": "Rabbids Party Theme",
        "m_artist": "Bin Party"
    },
    "42": {
        "m_file": "clubfling/muffledMusic",
        "m_title": "Club Fling Music",
        "m_artist": "Bin Party"
    },
    "43": {
        "m_file": "pirate/sailor",
        "m_title": "Pirate Party",
        "m_artist": "Bin Party"
    },
    "44": {
        "m_file": "pirate/rowrow",
        "m_title": "Pirate Party",
        "m_artist": "Bin Party"
    },
    "45": {
        "m_file": "madScientist/madScientistMusic_quiet",
        "m_title": "Mad Scientist Party",
        "m_artist": "Bin Party"
    },
    "46": {
        "m_file": "easter/KidsAtWork",
        "m_title": "Easter 1",
        "m_artist": "Bin Party"
    },
    "47": {
        "m_file": "easter/QuirkyBounce",
        "m_title": "Easter 2",
        "m_artist": "Bin Party"
    },
    "48": {
        "m_file": "rockNRoll/BinWeevils_RocknRoll1",
        "m_title": "Rock n Roll",
        "m_artist": "Bin Party"
    },
    "49": {
        "m_file": "rockNRoll/BinWeevils_RocknRoll2",
        "m_title": "Rock n Roll",
        "m_artist": "Bin Party"
    },
    "50": {
        "m_file": "halloween/BE_Halloween_Music_Sitting_Room_18_10_11vLow",
        "m_title": "Halloween2011",
        "m_artist": "Bin Party"
    },
    "51": {
        "m_file": "halloween/BE_Halloween_Music_Cafe_With_Cackle_19_10_11vLow",
        "m_title": "Halloween2011",
        "m_artist": "Bin Party"
    },
    "52": {
        "m_file": "innocent/innocentPartySong",
        "m_title": "Innocent Party",
        "m_artist": "Bin Party"
    },
    "53": {
        "m_file": "celebrity/BE_Fall_In_Flip_Out_New_Master_06_03_12",
        "m_title": "Celebrity Party",
        "m_artist": "Bin Party"
    },
    "54": {
        "m_file": "iceAge4/iceAgeParty",
        "m_title": "Ice Age 4",
        "m_artist": "Bin Party"
    },
    "55": {
        "m_file": "BWmusic/S0_Much_Better_With_Two_INST_LEAD",
        "m_title": "BWmusic1",
        "m_artist": "Bin Party"
    },
    "56": {
        "m_file": "BWmusic/The_Big_Bin_Weevil_Ball_INST_LEAD",
        "m_title": "BWmusic2",
        "m_artist": "Bin Party"
    },
    "57": {
        "m_file": "BWmusic/The_Great_Bin_Weevils_INST_LEAD",
        "m_title": "BWmusic3",
        "m_artist": "Bin Party"
    },
    "58": {
        "m_file": "fiesta_DanceAtTheRioGrande",
        "m_title": "Fiesta Tunes",
        "m_artist": "Bin Party"
    },
    "59": {
        "m_file": "SummerFair/SummerFair",
        "m_title": "Summer Fair",
        "m_artist": "Bin Party"
    },
    "60": {
        "m_file": "celebrity/BE_Fall_In_Flip_Out_New_Master_06_03_12",
        "m_title": "Fall In, Flip Out",
        "m_artist": "Bin Party"
    },
    "61": {
        "m_file": "halloween/CreepingAbout",
        "m_title": "Halloween Party",
        "m_artist": "Bin Party"
    },
    "62": {
        "m_file": "pirate/adventure",
        "m_title": "Pirate Party",
        "m_artist": "Bin Party"
    },
    "63": {
        "m_file": "SummerFair/FunHouse",
        "m_title": "Summer Fair - FunHouse",
        "m_artist": "Bin Party"
    },
    "64": {
        "m_file": "clarks/clarks",
        "m_title": "Clarks",
        "m_artist": "Bin Party"
    },
    "66": {
        "m_file": "christmas/jingleBells",
        "m_title": "Jingle Bells",
        "m_artist": "Bin Party"
    },
    "69": {
        "m_file": "christmas/funChristmas",
        "m_title": "Fun Christmas",
        "m_artist": "Bin Party"
    }
}